{"cameraMode":{"drawMode":0,"name":"Shaded","section":"Shading Mode"},"sceneLighting":true,"audioPlay":false,"sceneViewState":{"showFog":true,"showMaterialUpdate":false,"showSkybox":true,"showFlares":true,"showImageEffects":true,"showParticleSystems":true},"in2DMode":false,"pivot":{"x":1.9290435314178467,"y":-0.7968845367431641,"z":6.914583683013916},"rotation":{"x":-0.2684503495693207,"y":-0.10034524649381638,"z":0.028129326179623605,"w":-0.9576406478881836},"size":8.002888679504395,"orthographic":false}